its_us/__init__.py
its_us/circuits.py
its_us/gates.py
its_us/states.py
ITS_us-1.0.0.dist-info/LICENSE
ITS_us-1.0.0.dist-info/METADATA
ITS_us-1.0.0.dist-info/WHEEL
ITS_us-1.0.0.dist-info/top_level.txt
ITS_us-1.0.0.dist-info/RECORD
